wirecloud/__init__.py
wirecloud/catalogue/__init__.py
wirecloud/catalogue/admin.py
wirecloud/catalogue/models.py
wirecloud/catalogue/search_indexes.py
wirecloud/catalogue/urls.py
wirecloud/catalogue/utils.py
wirecloud/catalogue/views.py
wirecloud/catalogue/fixtures/catalogue_search_data.json
wirecloud/catalogue/fixtures/catalogue_test_data.json
wirecloud/catalogue/fixtures/selenium_test_data.json
wirecloud/catalogue/locale/ja/LC_MESSAGES/djangojs.mo
wirecloud/catalogue/management/__init__.py
wirecloud/catalogue/management/commands/__init__.py
wirecloud/catalogue/management/commands/addtocatalogue.py
wirecloud/catalogue/migrations/0001_initial.py
wirecloud/catalogue/migrations/0002_alter_json_description.py
wirecloud/catalogue/migrations/__init__.py
wirecloud/catalogue/signals/handlers.py
wirecloud/catalogue/static/js/wirecloud/WirecloudCatalogue.js
wirecloud/catalogue/static/js/wirecloud/WirecloudCatalogue/ResourceDetails.js
wirecloud/catalogue/static/js/wirecloud/ui/ResourcePainter.js
wirecloud/catalogue/static/js/wirecloud/ui/WirecloudCatalogue/ResourceDetailsView.js
wirecloud/catalogue/static/js/wirecloud/ui/WirecloudCatalogue/UploadWindowMenu.js
wirecloud/catalogue/tests/__init__.py
wirecloud/catalogue/tests/commands.py
wirecloud/catalogue/tests/selenium.py
wirecloud/catalogue/tests/tests.py
wirecloud/catalogue/tests/utils.py
wirecloud/catalogue/tests/test-data/basic_operator.zip
wirecloud/catalogue/tests/test-data/basic_widget.wgt
wirecloud/commons/__init__.py
wirecloud/commons/admin.py
wirecloud/commons/apps.py
wirecloud/commons/authentication.py
wirecloud/commons/compressor_precompilers.py
wirecloud/commons/exceptions.py
wirecloud/commons/fields.py
wirecloud/commons/haystack_fields.py
wirecloud/commons/haystack_queryparser.py
wirecloud/commons/middleware.py
wirecloud/commons/models.py
wirecloud/commons/search_indexes.py
wirecloud/commons/signals.py
wirecloud/commons/urls.py
wirecloud/commons/views.py
wirecloud/commons/wirecloud_admin.py
wirecloud-1.3.1.dist-info/LICENSE
wirecloud-1.3.1.dist-info/METADATA
wirecloud-1.3.1.dist-info/WHEEL
wirecloud-1.3.1.dist-info/entry_points.txt
wirecloud-1.3.1.dist-info/top_level.txt
wirecloud-1.3.1.dist-info/RECORD
