Metadata-Version: 2.1
Name: wirecloud
Version: 1.3.1
Summary: Widgets Container and Mashup edition tools for composing end-user centric mashup applications.
Home-page: http://github.com/Wirecloud/wirecloud
Author: CoNWeT Lab
Author-email: wirecloud@conwet.com
License: AGPLv3+ with classpath-like exception
Platform: UNKNOWN
Classifier: Development Status :: 5 - Production/Stable
Classifier: Environment :: Web Environment
Classifier: Framework :: Django
Classifier: Intended Audience :: Developers
Classifier: License :: OSI Approved :: GNU Affero General Public License v3 or later (AGPLv3+)
Classifier: Operating System :: OS Independent
Classifier: Programming Language :: Python
Classifier: Programming Language :: Python :: 3
Classifier: Programming Language :: Python :: 3.4
Classifier: Programming Language :: Python :: 3.5
Classifier: Programming Language :: JavaScript
Classifier: Topic :: Software Development :: Libraries :: Python Modules
Requires-Dist: Django (<1.12,>=1.10)
Requires-Dist: lxml (>=2.3)
Requires-Dist: django-appconf (<2.0,>=1.0.1)
Requires-Dist: django-compressor (<2.3,>=2.0)
Requires-Dist: rdflib (>=3.2.0)
Requires-Dist: requests (>=2.1.0)
Requires-Dist: selenium (>=3.4)
Requires-Dist: pytz
Requires-Dist: django-relatives (<1.0.0)
Requires-Dist: user-agents
Requires-Dist: regex
Requires-Dist: markdown
Requires-Dist: django-haystack (<2.8.0,>=2.6.0)
Requires-Dist: whoosh (>=2.7.2)
Requires-Dist: pycrypto
Requires-Dist: pyScss (<2.0,>=1.3.4)
Requires-Dist: Pygments
Requires-Dist: pillow
Requires-Dist: jsonpatch
